formencode/__init__.py
formencode/api.py
formencode/compound.py
formencode/context.py
formencode/declarative.py
formencode/doctest_xml_compare.py
formencode/exc.py
formencode/fieldstorage.py
formencode/foreach.py
formencode/htmlfill.py
formencode/htmlfill_schemabuilder.py
formencode/htmlgen.py
formencode/htmlrename.py
formencode/interfaces.py
formencode/national.py
formencode/rewritingparser.py
formencode/schema.py
formencode/validators.py
formencode/variabledecode.py
formencode/i18n/cs/LC_MESSAGES/FormEncode.mo
formencode/i18n/da/LC_MESSAGES/FormEncode.mo
formencode/i18n/de/LC_MESSAGES/FormEncode.mo
formencode/i18n/el/LC_MESSAGES/FormEncode.mo
formencode/i18n/es/LC_MESSAGES/FormEncode.mo
formencode/i18n/et/LC_MESSAGES/FormEncode.mo
formencode/i18n/fi/LC_MESSAGES/FormEncode.mo
formencode/i18n/fr/LC_MESSAGES/FormEncode.mo
formencode/i18n/it/LC_MESSAGES/FormEncode.mo
formencode/i18n/ja/LC_MESSAGES/FormEncode.mo
formencode/i18n/ko/LC_MESSAGES/FormEncode.mo
formencode/i18n/lt/LC_MESSAGES/FormEncode.mo
formencode/i18n/mk/LC_MESSAGES/FormEncode.mo
formencode/i18n/nb_NO/LC_MESSAGES/FormEncode.mo
formencode/i18n/nl/LC_MESSAGES/FormEncode.mo
formencode/i18n/pl/LC_MESSAGES/FormEncode.mo
formencode/i18n/pt_BR/LC_MESSAGES/FormEncode.mo
formencode/i18n/pt_PT/LC_MESSAGES/FormEncode.mo
formencode/i18n/ru/LC_MESSAGES/FormEncode.mo
formencode/i18n/sk/LC_MESSAGES/FormEncode.mo
formencode/i18n/sl/LC_MESSAGES/FormEncode.mo
formencode/i18n/sr/LC_MESSAGES/FormEncode.mo
formencode/i18n/sr@latin/LC_MESSAGES/FormEncode.mo
formencode/i18n/sv/LC_MESSAGES/FormEncode.mo
formencode/i18n/tr/LC_MESSAGES/FormEncode.mo
formencode/i18n/zh_CN/LC_MESSAGES/FormEncode.mo
formencode/i18n/zh_TW/LC_MESSAGES/FormEncode.mo
formencode/javascript/ordering.js
FormEncode-2.1.0.dist-info/LICENSE.txt
FormEncode-2.1.0.dist-info/METADATA
FormEncode-2.1.0.dist-info/WHEEL
FormEncode-2.1.0.dist-info/top_level.txt
FormEncode-2.1.0.dist-info/RECORD
