Metadata-Version: 2.1
Name: FormEncode
Version: 2.1.0
Summary: "HTML form validation, generation, and conversion package"
Home-page: https://www.formencode.org/
Author: Ian Bicking
Author-email: ianb@colorstudy.com
Maintainer: Chris Lambacher
Maintainer-email: chris@kateandchris.net
License: MIT
Classifier: Development Status :: 5 - Production/Stable
Classifier: Intended Audience :: Developers
Classifier: License :: OSI Approved :: MIT License
Classifier: Programming Language :: Python
Classifier: Programming Language :: Python :: 3
Classifier: Programming Language :: Python :: 3 :: Only
Classifier: Programming Language :: Python :: 3.7
Classifier: Programming Language :: Python :: 3.8
Classifier: Programming Language :: Python :: 3.9
Classifier: Programming Language :: Python :: 3.10
Classifier: Programming Language :: Python :: 3.11
Classifier: Programming Language :: Python :: 3.12
Classifier: Programming Language :: Python :: Implementation :: CPython
Classifier: Programming Language :: Python :: Implementation :: PyPy
Classifier: Topic :: Software Development :: Libraries :: Python Modules
Requires-Python: >=3.7
License-File: LICENSE.txt
Provides-Extra: testing
Requires-Dist: pytest; extra == "testing"
Requires-Dist: dnspython>=2; extra == "testing"
Requires-Dist: pycountry; extra == "testing"
